{
  "thana_geo": [
  {
    "thana": "Lalbagh",
    "geom": {
      "type": "Polygon",
      "coordinates": [
        [
          [
            90.38445711135864,
            23.71349971442111
          ],
          [
            90.38559436798094,
            23.71350953739825
          ],
          [
            90.38503646850586,
            23.71651042227937
          ],
          [
            90.38721442222595,
            23.71797891525138
          ],
          [
            90.38971960544586,
            23.71736008745293
          ],
          [
            90.39008438587189,
            23.71894153043458
          ],
          [
            90.388662815094,
            23.72319463286889
          ],
          [
            90.38944602012634,
            23.72747706234524
          ],
          [
            90.38747191429138,
            23.72966733313549
          ],
          [
            90.38701057434082,
            23.73254507692447
          ],
          [
            90.38206458091736,
            23.73218167933706
          ],
          [
            90.37782669067383,
            23.72917624423098
          ],
          [
            90.37738680839539,
            23.73029592423331
          ],
          [
            90.37554144859314,
            23.72970662016792
          ],
          [
            90.37707567214966,
            23.72609216361619
          ],
          [
            90.37453293800354,
            23.72267405272407
          ],
          [
            90.37874937057495,
            23.72000236342664
          ],
          [
            90.37972569465637,
            23.71549376361261
          ],
          [
            90.38445711135864,
            23.71349971442111
          ]
        ]
      ]
    }
  },
  {
    "thana": "Chawk Bazar",
    "geom": {
      "type": "Polygon",
      "coordinates": [
        [
          [
            90.3982812166214,
            23.71119620585741
          ],
          [
            90.40027141571045,
            23.71598490405463
          ],
          [
            90.39843678474426,
            23.71746813696266
          ],
          [
            90.39833217859268,
            23.72016688999267
          ],
          [
            90.40026605129242,
            23.72386008842349
          ],
          [
            90.39352297782898,
            23.7250412022796
          ],
          [
            90.38948893547058,
            23.72747706234524
          ],
          [
            90.38872718811035,
            23.72320445511579
          ],
          [
            90.39014339447021,
            23.71894153043458
          ],
          [
            90.38975715637207,
            23.71730115131897
          ],
          [
            90.38683891296387,
            23.71788068881277
          ],
          [
            90.38510084152222,
            23.71648586540014
          ],
          [
            90.38564801216125,
            23.71356847524553
          ],
          [
            90.38797616958618,
            23.71192802855174
          ],
          [
            90.3903579711914,
            23.71227183645378
          ],
          [
            90.39417743682861,
            23.71077872127328
          ],
          [
            90.3982812166214,
            23.71119620585741
          ]
        ]
      ]
    }
  },
  {
    "thana": "Kotwali",
    "geom": {
      "type": "Polygon",
      "coordinates": [
        [
          [
            90.3992360830307,
            23.71345059952433
          ],
          [
            90.39834558963774,
            23.71118638270606
          ],
          [
            90.41010975837706,
            23.70488467869911
          ],
          [
            90.41066765785217,
            23.70744861993827
          ],
          [
            90.4118800163269,
            23.70889265661851
          ],
          [
            90.41144013404846,
            23.71354882929939
          ],
          [
            90.4078459739685,
            23.71444271685293
          ],
          [
            90.40361881256104,
            23.71275316599433
          ],
          [
            90.40328621864319,
            23.71149581161786
          ],
          [
            90.3992360830307,
            23.71345059952433
          ]
        ]
      ]
    }
  }
]
}